trajdata/__init__.py
trajdata/dataset.py
trajdata/augmentation/__init__.py
trajdata/augmentation/augmentation.py
trajdata/augmentation/low_vel_yaw_correction.py
trajdata/augmentation/noise_histories.py
trajdata/caching/__init__.py
trajdata/caching/df_cache.py
trajdata/caching/env_cache.py
trajdata/caching/scene_cache.py
trajdata/data_structures/__init__.py
trajdata/data_structures/agent.py
trajdata/data_structures/batch.py
trajdata/data_structures/batch_element.py
trajdata/data_structures/collation.py
trajdata/data_structures/data_index.py
trajdata/data_structures/environment.py
trajdata/data_structures/scene.py
trajdata/data_structures/scene_metadata.py
trajdata/data_structures/scene_tag.py
trajdata/data_structures/state.py
trajdata/dataset_specific/__init__.py
trajdata/dataset_specific/raw_dataset.py
trajdata/dataset_specific/scene_records.py
trajdata/dataset_specific/eth_ucy_peds/__init__.py
trajdata/dataset_specific/eth_ucy_peds/eupeds_dataset.py
trajdata/dataset_specific/interaction/__init__.py
trajdata/dataset_specific/interaction/interaction_dataset.py
trajdata/dataset_specific/lyft/__init__.py
trajdata/dataset_specific/lyft/lyft_dataset.py
trajdata/dataset_specific/lyft/lyft_utils.py
trajdata/dataset_specific/nuplan/__init__.py
trajdata/dataset_specific/nuplan/nuplan_dataset.py
trajdata/dataset_specific/nuplan/nuplan_utils.py
trajdata/dataset_specific/nusc/__init__.py
trajdata/dataset_specific/nusc/nusc_dataset.py
trajdata/dataset_specific/nusc/nusc_utils.py
trajdata/dataset_specific/sdd_peds/__init__.py
trajdata/dataset_specific/sdd_peds/estimated_homography.py
trajdata/dataset_specific/sdd_peds/sddpeds_dataset.py
trajdata/dataset_specific/waymo/__init__.py
trajdata/dataset_specific/waymo/waymo_dataset.py
trajdata/dataset_specific/waymo/waymo_utils.py
trajdata/filtering/__init__.py
trajdata/filtering/filters.py
trajdata/maps/__init__.py
trajdata/maps/lane_route.py
trajdata/maps/map_api.py
trajdata/maps/map_kdtree.py
trajdata/maps/map_strtree.py
trajdata-1.4.0.dist-info/LICENSE
trajdata-1.4.0.dist-info/METADATA
trajdata-1.4.0.dist-info/WHEEL
trajdata-1.4.0.dist-info/top_level.txt
trajdata-1.4.0.dist-info/RECORD
