Metadata-Version: 2.1
Name: trajdata
Version: 1.4.0
Summary: A unified interface to many trajectory forecasting datasets.
Author-email: Boris Ivanovic <bivanovic@nvidia.com>
Project-URL: Homepage, https://github.com/nvr-avg/trajdata
Project-URL: Bug Tracker, https://github.com/nvr-avg/trajdata/issues
Classifier: Development Status :: 3 - Alpha
Classifier: Intended Audience :: Developers
Classifier: Programming Language :: Python :: 3.8
Classifier: License :: OSI Approved :: Apache Software License
Requires-Python: >=3.8
License-File: LICENSE
Requires-Dist: numpy >=1.19
Requires-Dist: tqdm >=4.62
Requires-Dist: matplotlib >=3.5
Requires-Dist: dill >=0.3.4
Requires-Dist: pandas >=1.4.1
Requires-Dist: pyarrow >=7.0.0
Requires-Dist: torch >=1.10.2
Requires-Dist: zarr >=2.11.0
Requires-Dist: kornia >=0.6.4
Requires-Dist: seaborn >=0.12
Requires-Dist: bokeh >=3.0.3
Requires-Dist: geopandas >=0.13.2
Requires-Dist: protobuf ==3.19.4
Requires-Dist: scipy >=1.9.0
Requires-Dist: opencv-python >=4.5.0
Requires-Dist: shapely >=2.0.0
Provides-Extra: dev
Requires-Dist: black ; extra == 'dev'
Requires-Dist: isort ; extra == 'dev'
Requires-Dist: pytest ; extra == 'dev'
Requires-Dist: pytest-xdist ; extra == 'dev'
Requires-Dist: twine ; extra == 'dev'
Requires-Dist: build ; extra == 'dev'
Provides-Extra: interaction
Requires-Dist: lanelet2 ==1.2.1 ; extra == 'interaction'
Provides-Extra: lyft
Requires-Dist: l5kit ==1.5.0 ; extra == 'lyft'
Provides-Extra: nusc
Requires-Dist: nuscenes-devkit ==1.1.9 ; extra == 'nusc'
Provides-Extra: waymo
Requires-Dist: tensorflow ==2.11.0 ; extra == 'waymo'
Requires-Dist: waymo-open-dataset-tf-2-11-0 ; extra == 'waymo'
Requires-Dist: intervaltree ; extra == 'waymo'
